README.rst
setup.py
amqpy/__init__.py
amqpy/abstract_channel.py
amqpy/channel.py
amqpy/compat.py
amqpy/concurrency.py
amqpy/connection.py
amqpy/consumer.py
amqpy/exceptions.py
amqpy/login.py
amqpy/message.py
amqpy/method_io.py
amqpy/proto.py
amqpy/serialization.py
amqpy/spec.py
amqpy/transport.py
amqpy/utils.py
amqpy.egg-info/PKG-INFO
amqpy.egg-info/SOURCES.txt
amqpy.egg-info/dependency_links.txt
amqpy.egg-info/requires.txt
amqpy.egg-info/top_level.txt
amqpy/support/__init__.py
amqpy/support/monotonic.py
amqpy/tests/__init__.py
amqpy/tests/conftest.py
amqpy/tests/test_basic_message.py
amqpy/tests/test_channel.py
amqpy/tests/test_connection.py
amqpy/tests/test_consumer.py
amqpy/tests/test_serialization.py
amqpy/tests/test_with.py