Metadata-Version: 1.1
Name: amqpy
Version: 0.13.0
Summary: an AMQP 0.9.1 client library for Python 2.7 & Python >= 3.2.0
Home-page: http://github.com/veegee/amqpy
Author: veegee
Author-email: veegee@veegee.org
License: LGPL
Keywords: amqp,rabbitmq,qpid
Platform: any
Classifier: Development Status :: 4 - Beta
Classifier: Programming Language :: Python
Classifier: Programming Language :: Python :: Implementation :: CPython
Classifier: Programming Language :: Python :: Implementation :: PyPy
Classifier: Programming Language :: Python :: 2.7
Classifier: Programming Language :: Python :: 3.2
Classifier: Programming Language :: Python :: 3.3
Classifier: Programming Language :: Python :: 3.4
Classifier: Programming Language :: Python :: 3.5
Classifier: License :: OSI Approved :: MIT License
Classifier: Intended Audience :: Developers
Classifier: Topic :: Internet
Classifier: Topic :: Software Development :: Libraries :: Python Modules
Classifier: Topic :: System :: Networking
